LICENSE
dionpy/IonFrame.py
dionpy/IonModel.py
dionpy/__init__.py
dionpy/modules/__init__.py
dionpy/modules/col_freq_agg.csv
dionpy/modules/collision_models.py
dionpy/modules/helpers.py
dionpy/modules/ion_tools.py
dionpy/modules/parallel.py
dionpy/modules/parallel_iri.py
dionpy/modules/plotting.py
dionpy/raytracing.py
dionpy-1.2.1.dist-info/LICENSE
dionpy-1.2.1.dist-info/METADATA
dionpy-1.2.1.dist-info/WHEEL
dionpy-1.2.1.dist-info/RECORD
