Metadata-Version: 2.1
Name: dionpy
Version: 1.2.1
Summary: Dynamic ionosphere model for global 21 cm experiments
Home-page: https://github.com/lap1dem/dionpy
License: MIT
Author: Vadym Bidula
Author-email: vadym.bidula@gmail.com
Requires-Python: >=3.9,<4.0
Classifier: License :: OSI Approved :: MIT License
Classifier: Programming Language :: Python :: 3
Classifier: Programming Language :: Python :: 3.9
Classifier: Programming Language :: Python :: 3.10
Classifier: Programming Language :: Python :: 3.11
Classifier: Programming Language :: Python :: 3.12
Provides-Extra: numba
Requires-Dist: echaim (>=1.1.3,<2.0.0)
Requires-Dist: ffmpeg-progress-yield (>=0.7.8,<0.8.0)
Requires-Dist: h5py (>=3.7.0,<4.0.0)
Requires-Dist: healpy (>=1.16.1,<2.0.0)
Requires-Dist: iricore (>=1.8.3,<2.0.0)
Requires-Dist: it (>=1.0.0,<2.0.0)
Requires-Dist: matplotlib (>=3.6.0,<4.0.0)
Requires-Dist: numpy (>=1.22,<2.0)
Requires-Dist: pymap3d (>=3.0.1,<4.0.0)
Requires-Dist: pytz (>=2023.3,<2024.0)
Requires-Dist: scipy (>=1.9.3,<2.0.0)
Requires-Dist: skyfield (>=1.46,<2.0)
Requires-Dist: tqdm (>=4.66,<5.0)
Project-URL: Repository, https://github.com/lap1dem/dionpy
